{
    "_links": {
        "self": {
            "href": "https:\/\/dev-botdemo.pantheonsite.io\/components\/3?_format=hal_json"
        },
        "type": {
            "href": "https:\/\/dev-botdemo.pantheonsite.io\/rest\/type\/components\/simple_title_and_body"
        },
        "https:\/\/dev-botdemo.pantheonsite.io\/rest\/relation\/components\/simple_title_and_body\/uid": [
            {
                "href": "https:\/\/dev-botdemo.pantheonsite.io\/user\/1?_format=hal_json",
                "lang": "en"
            }
        ],
        "https:\/\/dev-botdemo.pantheonsite.io\/rest\/relation\/components\/simple_title_and_body\/field_layout_width_text": [
            null
        ]
    },
    "uuid": [
        {
            "value": "cdd50140-fde0-4123-98c1-7d7c950f0118"
        }
    ],
    "langcode": [
        {
            "value": "en",
            "lang": "en"
        }
    ],
    "type": [
        {
            "target_id": "simple_title_and_body"
        }
    ],
    "title": [
        {
            "value": "Intro Text",
            "lang": "en"
        }
    ],
    "_embedded": {
        "https:\/\/dev-botdemo.pantheonsite.io\/rest\/relation\/components\/simple_title_and_body\/uid": [
            {
                "_links": {
                    "self": {
                        "href": "https:\/\/dev-botdemo.pantheonsite.io\/user\/1?_format=hal_json"
                    },
                    "type": {
                        "href": "https:\/\/dev-botdemo.pantheonsite.io\/rest\/type\/user\/user"
                    }
                },
                "uuid": [
                    {
                        "value": "acdfcba1-884c-4b96-8000-232f9d10fe74"
                    }
                ],
                "lang": "en"
            }
        ],
        "https:\/\/dev-botdemo.pantheonsite.io\/rest\/relation\/components\/simple_title_and_body\/field_layout_width_text": [
            null
        ]
    },
    "created": [
        {
            "value": "2020-07-21T16:45:56+00:00",
            "lang": "en",
            "format": "Y-m-d\\TH:i:sP"
        }
    ],
    "changed": [
        {
            "value": "2020-08-13T14:43:43+00:00",
            "lang": "en",
            "format": "Y-m-d\\TH:i:sP"
        }
    ],
    "default_langcode": [
        {
            "value": true,
            "lang": "en"
        }
    ],
    "metatag": [
        {
            "value": {
                "title": "Default Content Deploy - Export | BackOffice Theme",
                "canonical_url": "https:\/\/dev-botdemo.pantheonsite.io\/admin\/config\/development\/dcd\/export"
            }
        }
    ],
    "field_body": [
        {
            "value": "<h2 class=\"text-align-center\">WIDE Credo in Deum Patrem omnipotentem<\/h2>\r\n\r\n<p>Creatorem caeli et terrae. Et in Iesum Christum, Filium eius unicum, Dominum nostrum, qui conceptus est de Spiritu Sancto, natus ex Maria Virgine, passus sub Pontio Pilato, crucifixus, mortuus, et sepultus, descendit ad infernos, tertia die resurrexit a mortuis, ascendit ad caelos, sedet ad dexteram Dei Patris omnipotentis, inde venturus est iudicare vivos et mortuos. Credo in Spiritum Sanctum, sanctam Ecclesiam catholicam, sanctorum communionem, remissionem peccatorum, carnis resurrectionem, vitam aeternam.<\/p>\r\n\r\n<p>Pater noster, qui es in caelis, sanctificetur nomen tuum. Adveniat regnum tuum. Fiat voluntas tua, sicut in caelo et in terra. Panem nostrum quotidianum da nobis hodie, et dimitte nobis debita nostra sicut et nos dimittimus debitoribus nostris. Et ne nos inducas in tentationem, sed libera nos a malo. Ave maria, gratia plena, Dominus tecum. Benedicta tu in mulieribus, et benedictus fructus ventris tui, Iesus. Sancta Maria, Mater Dei, ora pro nobis peccatoribus, nunc, et in hora mortis nostrae. Amen.<\/p>\r\n",
            "format": "basic_html",
            "processed": "<h2 class=\"text-align-center\">WIDE Credo in Deum Patrem omnipotentem<\/h2>\n\n<p>Creatorem caeli et terrae. Et in Iesum Christum, Filium eius unicum, Dominum nostrum, qui conceptus est de Spiritu Sancto, natus ex Maria Virgine, passus sub Pontio Pilato, crucifixus, mortuus, et sepultus, descendit ad infernos, tertia die resurrexit a mortuis, ascendit ad caelos, sedet ad dexteram Dei Patris omnipotentis, inde venturus est iudicare vivos et mortuos. Credo in Spiritum Sanctum, sanctam Ecclesiam catholicam, sanctorum communionem, remissionem peccatorum, carnis resurrectionem, vitam aeternam.<\/p>\n\n<p>Pater noster, qui es in caelis, sanctificetur nomen tuum. Adveniat regnum tuum. Fiat voluntas tua, sicut in caelo et in terra. Panem nostrum quotidianum da nobis hodie, et dimitte nobis debita nostra sicut et nos dimittimus debitoribus nostris. Et ne nos inducas in tentationem, sed libera nos a malo. Ave maria, gratia plena, Dominus tecum. Benedicta tu in mulieribus, et benedictus fructus ventris tui, Iesus. Sancta Maria, Mater Dei, ora pro nobis peccatoribus, nunc, et in hora mortis nostrae. Amen.<\/p>\n"
        }
    ]
}