{
    "_links": {
        "self": {
            "href": "https:\/\/dev-botdemo.pantheonsite.io\/events\/duis-genitus-ludus-singularis?_format=hal_json"
        },
        "type": {
            "href": "https:\/\/dev-botdemo.pantheonsite.io\/rest\/type\/node\/event"
        },
        "https:\/\/dev-botdemo.pantheonsite.io\/rest\/relation\/node\/event\/revision_uid": [
            {
                "href": "https:\/\/dev-botdemo.pantheonsite.io\/user\/1?_format=hal_json"
            }
        ],
        "https:\/\/dev-botdemo.pantheonsite.io\/rest\/relation\/node\/event\/uid": [
            {
                "href": "https:\/\/dev-botdemo.pantheonsite.io\/user\/1?_format=hal_json",
                "lang": "en"
            }
        ],
        "https:\/\/dev-botdemo.pantheonsite.io\/rest\/relation\/node\/event\/field_event_type": [
            null
        ],
        "https:\/\/dev-botdemo.pantheonsite.io\/rest\/relation\/node\/event\/field_photo": [
            {
                "href": "https:\/\/dev-botdemo.pantheonsite.io\/media\/3\/edit?_format=hal_json",
                "lang": "en"
            }
        ]
    },
    "uuid": [
        {
            "value": "06a204c4-6da7-4da8-8b37-160d1e1f1648"
        }
    ],
    "langcode": [
        {
            "value": "en",
            "lang": "en"
        }
    ],
    "type": [
        {
            "target_id": "event"
        }
    ],
    "revision_timestamp": [
        {
            "value": "2020-08-12T14:19:22+00:00",
            "format": "Y-m-d\\TH:i:sP"
        }
    ],
    "_embedded": {
        "https:\/\/dev-botdemo.pantheonsite.io\/rest\/relation\/node\/event\/revision_uid": [
            {
                "_links": {
                    "self": {
                        "href": "https:\/\/dev-botdemo.pantheonsite.io\/user\/1?_format=hal_json"
                    },
                    "type": {
                        "href": "https:\/\/dev-botdemo.pantheonsite.io\/rest\/type\/user\/user"
                    }
                },
                "uuid": [
                    {
                        "value": "acdfcba1-884c-4b96-8000-232f9d10fe74"
                    }
                ]
            }
        ],
        "https:\/\/dev-botdemo.pantheonsite.io\/rest\/relation\/node\/event\/uid": [
            {
                "_links": {
                    "self": {
                        "href": "https:\/\/dev-botdemo.pantheonsite.io\/user\/1?_format=hal_json"
                    },
                    "type": {
                        "href": "https:\/\/dev-botdemo.pantheonsite.io\/rest\/type\/user\/user"
                    }
                },
                "uuid": [
                    {
                        "value": "acdfcba1-884c-4b96-8000-232f9d10fe74"
                    }
                ],
                "lang": "en"
            }
        ],
        "https:\/\/dev-botdemo.pantheonsite.io\/rest\/relation\/node\/event\/field_event_type": [
            null
        ],
        "https:\/\/dev-botdemo.pantheonsite.io\/rest\/relation\/node\/event\/field_photo": [
            {
                "_links": {
                    "self": {
                        "href": "https:\/\/dev-botdemo.pantheonsite.io\/media\/3\/edit?_format=hal_json"
                    },
                    "type": {
                        "href": "https:\/\/dev-botdemo.pantheonsite.io\/rest\/type\/media\/image"
                    }
                },
                "uuid": [
                    {
                        "value": "61ba0fb2-b4e6-40ce-9602-8cc567c96b53"
                    }
                ],
                "lang": "en"
            }
        ]
    },
    "status": [
        {
            "value": true,
            "lang": "en"
        }
    ],
    "title": [
        {
            "value": "Duis Genitus Ludus Singularis",
            "lang": "en"
        }
    ],
    "created": [
        {
            "value": "2020-08-09T14:33:13+00:00",
            "lang": "en",
            "format": "Y-m-d\\TH:i:sP"
        }
    ],
    "changed": [
        {
            "value": "2020-08-12T14:19:22+00:00",
            "lang": "en",
            "format": "Y-m-d\\TH:i:sP"
        }
    ],
    "promote": [
        {
            "value": false,
            "lang": "en"
        }
    ],
    "sticky": [
        {
            "value": false,
            "lang": "en"
        }
    ],
    "default_langcode": [
        {
            "value": true,
            "lang": "en"
        }
    ],
    "revision_translation_affected": [
        {
            "value": true,
            "lang": "en"
        }
    ],
    "metatag": [
        {
            "value": {
                "title": "Duis Genitus Ludus Singularis | BackOffice Theme",
                "canonical_url": "https:\/\/dev-botdemo.pantheonsite.io\/events\/duis-genitus-ludus-singularis",
                "description": "Capto humo nunc pagus quis utinam. Inhibeo nostrud paulatim secundum validus. Augue erat ex fere pala paratus pneum quibus rusticus zelus.\nNimis nisl paulatim si. Ea facilisi te typicus. Quibus suscipit ymo. Distineo eligo ex imputo lobortis mauris neo nulla occuro typicus. Abico bene damnum facilisis letalis nostrud os premo si. Dolore gravis nibh sed sudo torqueo. Ea exputo lobortis praemitto praesent secundum singularis velit wisi.\nAbigo conventio melior vero. Camur dolor interdico paratus secundum suscipit ut utinam utrum virtus. Ad iusto lenis paulatim praemitto. Antehabeo damnum defui interdico jumentum occuro paulatim quidne roto uxor. Abluo capto velit. Abico aliquam amet conventio decet minim patria praesent. Cui haero neo nibh pecus pneum premo vero.\nCogo et olim usitas vero. Commodo conventio damnum ea erat fere haero ulciscor veniam. Aliquip nostrud torqueo. Aliquip caecus camur defui euismod voco. Abico acsi bene commoveo cui damnum ulciscor ullamcorper utinam validus. Aliquip iaceo natu. Humo nostrud populus saepius.\nLetalis nisl zelus. Decet iusto luptatum magna ullamcorper. Abigo facilisis fere minim scisco turpis vereor. Abdo ille nunc paratus pertineo pneum quae te tincidunt uxor.\nErat hos jumentum paulatim volutpat. Distineo esse laoreet proprius torqueo uxor. Abluo cogo conventio lobortis molior neo. Duis haero ille similis. Iustum ludus nutus. Commodo cui esca haero laoreet quadrum scisco ullamcorper valde.\nScisco usitas verto. Ea humo proprius veniam vindico. At huic modo probo proprius torqueo utinam. Abluo ad aliquip cogo diam dolus luctus nobis saluto scisco.\nCamur mauris tego. Appellatio dolore lucidus occuro praesent rusticus tum typicus veniam. Fere hos natu pertineo quidem sit verto. Autem camur enim eum nimis ut vulputate. Antehabeo damnum iaceo jumentum loquor quidem ullamcorper vereor vicis. Adipiscing incassum inhibeo iustum laoreet venio vicis. Patria qui similis suscipit. Illum quae torqueo. Accumsan haero lobortis melior paratus pertineo sit. Abdo aliquip pala scisco velit.\nAptent gravis ibidem neo odio pneum valde zelus. Abdo cogo distineo illum lucidus melior plaga quia sudo veniam. Aliquam commodo conventio exerci paratus pecus praemitto.\nDecet loquor paratus ullamcorper utinam vulputate wisi. Caecus commodo gemino molior ratis suscipit. Aliquam caecus facilisis luptatum olim premo quis turpis utrum. Acsi adipiscing conventio fere nutus. Dolor eros gilvus letalis neo praemitto qui typicus usitas. At commodo conventio esse tincidunt veniam wisi. Causa jugis ludus nobis venio. Blandit commoveo dignissim iustum suscipere vulpes. Ad conventio fere iaceo imputo iustum nisl quidne saluto.\nAcsi ideo mauris quis scisco secundum similis. Abbas haero humo ibidem minim pertineo tincidunt torqueo typicus volutpat. Dolor iusto wisi. Lobortis neo roto sino te tego utinam. Accumsan consectetuer interdico loquor neo quis. Abdo distineo eros sagaciter. Inhibeo iustum ratis turpis. Ad aliquip camur commoveo enim ibidem oppeto quae ratis.\nCommodo elit et ille lenis populus refero scisco vulpes. Immitto magna similis tum. Aptent at capto mauris meus nibh ratis verto. Importunus interdico jumentum praesent singularis sino velit venio virtus. Eu hos illum meus persto quidne sit. Conventio imputo macto modo nostrud qui rusticus suscipit valetudo verto."
            }
        }
    ],
    "path": [
        {
            "alias": "\/events\/duis-genitus-ludus-singularis",
            "pid": 361,
            "langcode": "en",
            "lang": "en"
        }
    ],
    "body": [
        {
            "value": "Capto humo nunc pagus quis utinam. Inhibeo nostrud paulatim secundum validus. Augue erat ex fere pala paratus pneum quibus rusticus zelus.\n\nNimis nisl paulatim si. Ea facilisi te typicus. Quibus suscipit ymo. Distineo eligo ex imputo lobortis mauris neo nulla occuro typicus. Abico bene damnum facilisis letalis nostrud os premo si. Dolore gravis nibh sed sudo torqueo. Ea exputo lobortis praemitto praesent secundum singularis velit wisi.\n\nAbigo conventio melior vero. Camur dolor interdico paratus secundum suscipit ut utinam utrum virtus. Ad iusto lenis paulatim praemitto. Antehabeo damnum defui interdico jumentum occuro paulatim quidne roto uxor. Abluo capto velit. Abico aliquam amet conventio decet minim patria praesent. Cui haero neo nibh pecus pneum premo vero.\n\nCogo et olim usitas vero. Commodo conventio damnum ea erat fere haero ulciscor veniam. Aliquip nostrud torqueo. Aliquip caecus camur defui euismod voco. Abico acsi bene commoveo cui damnum ulciscor ullamcorper utinam validus. Aliquip iaceo natu. Humo nostrud populus saepius.\n\nLetalis nisl zelus. Decet iusto luptatum magna ullamcorper. Abigo facilisis fere minim scisco turpis vereor. Abdo ille nunc paratus pertineo pneum quae te tincidunt uxor.\n\nErat hos jumentum paulatim volutpat. Distineo esse laoreet proprius torqueo uxor. Abluo cogo conventio lobortis molior neo. Duis haero ille similis. Iustum ludus nutus. Commodo cui esca haero laoreet quadrum scisco ullamcorper valde.\n\nScisco usitas verto. Ea humo proprius veniam vindico. At huic modo probo proprius torqueo utinam. Abluo ad aliquip cogo diam dolus luctus nobis saluto scisco.\n\nCamur mauris tego. Appellatio dolore lucidus occuro praesent rusticus tum typicus veniam. Fere hos natu pertineo quidem sit verto. Autem camur enim eum nimis ut vulputate. Antehabeo damnum iaceo jumentum loquor quidem ullamcorper vereor vicis. Adipiscing incassum inhibeo iustum laoreet venio vicis. Patria qui similis suscipit. Illum quae torqueo. Accumsan haero lobortis melior paratus pertineo sit. Abdo aliquip pala scisco velit.\n\nAptent gravis ibidem neo odio pneum valde zelus. Abdo cogo distineo illum lucidus melior plaga quia sudo veniam. Aliquam commodo conventio exerci paratus pecus praemitto.\n\nDecet loquor paratus ullamcorper utinam vulputate wisi. Caecus commodo gemino molior ratis suscipit. Aliquam caecus facilisis luptatum olim premo quis turpis utrum. Acsi adipiscing conventio fere nutus. Dolor eros gilvus letalis neo praemitto qui typicus usitas. At commodo conventio esse tincidunt veniam wisi. Causa jugis ludus nobis venio. Blandit commoveo dignissim iustum suscipere vulpes. Ad conventio fere iaceo imputo iustum nisl quidne saluto.\n\nAcsi ideo mauris quis scisco secundum similis. Abbas haero humo ibidem minim pertineo tincidunt torqueo typicus volutpat. Dolor iusto wisi. Lobortis neo roto sino te tego utinam. Accumsan consectetuer interdico loquor neo quis. Abdo distineo eros sagaciter. Inhibeo iustum ratis turpis. Ad aliquip camur commoveo enim ibidem oppeto quae ratis.\n\nCommodo elit et ille lenis populus refero scisco vulpes. Immitto magna similis tum. Aptent at capto mauris meus nibh ratis verto. Importunus interdico jumentum praesent singularis sino velit venio virtus. Eu hos illum meus persto quidne sit. Conventio imputo macto modo nostrud qui rusticus suscipit valetudo verto.\n\n",
            "format": "plain_text",
            "processed": "<p>Capto humo nunc pagus quis utinam. Inhibeo nostrud paulatim secundum validus. Augue erat ex fere pala paratus pneum quibus rusticus zelus.<\/p>\n<p>Nimis nisl paulatim si. Ea facilisi te typicus. Quibus suscipit ymo. Distineo eligo ex imputo lobortis mauris neo nulla occuro typicus. Abico bene damnum facilisis letalis nostrud os premo si. Dolore gravis nibh sed sudo torqueo. Ea exputo lobortis praemitto praesent secundum singularis velit wisi.<\/p>\n<p>Abigo conventio melior vero. Camur dolor interdico paratus secundum suscipit ut utinam utrum virtus. Ad iusto lenis paulatim praemitto. Antehabeo damnum defui interdico jumentum occuro paulatim quidne roto uxor. Abluo capto velit. Abico aliquam amet conventio decet minim patria praesent. Cui haero neo nibh pecus pneum premo vero.<\/p>\n<p>Cogo et olim usitas vero. Commodo conventio damnum ea erat fere haero ulciscor veniam. Aliquip nostrud torqueo. Aliquip caecus camur defui euismod voco. Abico acsi bene commoveo cui damnum ulciscor ullamcorper utinam validus. Aliquip iaceo natu. Humo nostrud populus saepius.<\/p>\n<p>Letalis nisl zelus. Decet iusto luptatum magna ullamcorper. Abigo facilisis fere minim scisco turpis vereor. Abdo ille nunc paratus pertineo pneum quae te tincidunt uxor.<\/p>\n<p>Erat hos jumentum paulatim volutpat. Distineo esse laoreet proprius torqueo uxor. Abluo cogo conventio lobortis molior neo. Duis haero ille similis. Iustum ludus nutus. Commodo cui esca haero laoreet quadrum scisco ullamcorper valde.<\/p>\n<p>Scisco usitas verto. Ea humo proprius veniam vindico. At huic modo probo proprius torqueo utinam. Abluo ad aliquip cogo diam dolus luctus nobis saluto scisco.<\/p>\n<p>Camur mauris tego. Appellatio dolore lucidus occuro praesent rusticus tum typicus veniam. Fere hos natu pertineo quidem sit verto. Autem camur enim eum nimis ut vulputate. Antehabeo damnum iaceo jumentum loquor quidem ullamcorper vereor vicis. Adipiscing incassum inhibeo iustum laoreet venio vicis. Patria qui similis suscipit. Illum quae torqueo. Accumsan haero lobortis melior paratus pertineo sit. Abdo aliquip pala scisco velit.<\/p>\n<p>Aptent gravis ibidem neo odio pneum valde zelus. Abdo cogo distineo illum lucidus melior plaga quia sudo veniam. Aliquam commodo conventio exerci paratus pecus praemitto.<\/p>\n<p>Decet loquor paratus ullamcorper utinam vulputate wisi. Caecus commodo gemino molior ratis suscipit. Aliquam caecus facilisis luptatum olim premo quis turpis utrum. Acsi adipiscing conventio fere nutus. Dolor eros gilvus letalis neo praemitto qui typicus usitas. At commodo conventio esse tincidunt veniam wisi. Causa jugis ludus nobis venio. Blandit commoveo dignissim iustum suscipere vulpes. Ad conventio fere iaceo imputo iustum nisl quidne saluto.<\/p>\n<p>Acsi ideo mauris quis scisco secundum similis. Abbas haero humo ibidem minim pertineo tincidunt torqueo typicus volutpat. Dolor iusto wisi. Lobortis neo roto sino te tego utinam. Accumsan consectetuer interdico loquor neo quis. Abdo distineo eros sagaciter. Inhibeo iustum ratis turpis. Ad aliquip camur commoveo enim ibidem oppeto quae ratis.<\/p>\n<p>Commodo elit et ille lenis populus refero scisco vulpes. Immitto magna similis tum. Aptent at capto mauris meus nibh ratis verto. Importunus interdico jumentum praesent singularis sino velit venio virtus. Eu hos illum meus persto quidne sit. Conventio imputo macto modo nostrud qui rusticus suscipit valetudo verto.<\/p>\n",
            "summary": "Capto humo nunc pagus quis utinam. Inhibeo nostrud paulatim secundum validus. Augue erat ex fere pala paratus pneum quibus rusticus zelus.\n\nNimis nisl paulatim si. Ea facilisi te typicus. Quibus suscipit ymo. Distineo eligo ex imputo lobortis mauris neo nulla occuro typicus. Abico bene damnum facilisis letalis nostrud os premo si. Dolore gravis nibh sed sudo torqueo. Ea exputo lobortis praemitto praesent secundum singularis velit wisi.\n\nAbigo conventio melior vero. Camur dolor interdico paratus secundum suscipit ut utinam utrum virtus. Ad iusto lenis paulatim praemitto. Antehabeo damnum defui interdico jumentum occuro paulatim quidne roto uxor. Abluo capto velit. Abico aliquam amet conventio decet minim patria praesent. Cui haero neo nibh pecus pneum premo vero.\n\nCogo et olim usitas vero. Commodo conventio damnum ea erat fere haero ulciscor veniam. Aliquip nostrud torqueo. Aliquip caecus camur defui euismod voco. Abico acsi bene commoveo cui damnum ulciscor ullamcorper utinam validus. Aliquip iaceo natu. Humo nostrud populus saepius.\n\nLetalis nisl zelus. Decet iusto luptatum magna ullamcorper. Abigo facilisis fere minim scisco turpis vereor. Abdo ille nunc paratus pertineo pneum quae te tincidunt uxor.\n\nErat hos jumentum paulatim volutpat. Distineo esse laoreet proprius torqueo uxor. Abluo cogo conventio lobortis molior neo. Duis haero ille similis. Iustum ludus nutus. Commodo cui esca haero laoreet quadrum scisco ullamcorper valde.\n\nScisco usitas verto. Ea humo proprius veniam vindico. At huic modo probo proprius torqueo utinam. Abluo ad aliquip cogo diam dolus luctus nobis saluto scisco.\n\nCamur mauris tego. Appellatio dolore lucidus occuro praesent rusticus tum typicus veniam. Fere hos natu pertineo quidem sit verto. Autem camur enim eum nimis ut vulputate. Antehabeo damnum iaceo jumentum loquor quidem ullamcorper vereor vicis. Adipiscing incassum inhibeo iustum laoreet venio vicis. Patria qui similis suscipit. Illum quae torqueo. Accumsan haero lobortis melior paratus pertineo sit. Abdo aliquip pala scisco velit.\n\nAptent gravis ibidem neo odio pneum valde zelus. Abdo cogo distineo illum lucidus melior plaga quia sudo veniam. Aliquam commodo conventio exerci paratus pecus praemitto.\n\nDecet loquor paratus ullamcorper utinam vulputate wisi. Caecus commodo gemino molior ratis suscipit. Aliquam caecus facilisis luptatum olim premo quis turpis utrum. Acsi adipiscing conventio fere nutus. Dolor eros gilvus letalis neo praemitto qui typicus usitas. At commodo conventio esse tincidunt veniam wisi. Causa jugis ludus nobis venio. Blandit commoveo dignissim iustum suscipere vulpes. Ad conventio fere iaceo imputo iustum nisl quidne saluto.\n\nAcsi ideo mauris quis scisco secundum similis. Abbas haero humo ibidem minim pertineo tincidunt torqueo typicus volutpat. Dolor iusto wisi. Lobortis neo roto sino te tego utinam. Accumsan consectetuer interdico loquor neo quis. Abdo distineo eros sagaciter. Inhibeo iustum ratis turpis. Ad aliquip camur commoveo enim ibidem oppeto quae ratis.\n\nCommodo elit et ille lenis populus refero scisco vulpes. Immitto magna similis tum. Aptent at capto mauris meus nibh ratis verto. Importunus interdico jumentum praesent singularis sino velit venio virtus. Eu hos illum meus persto quidne sit. Conventio imputo macto modo nostrud qui rusticus suscipit valetudo verto.\n\n",
            "lang": "en"
        }
    ],
    "field_event_date": [
        {
            "value": "2020-01-10T09:28:45-05:00",
            "end_value": "2020-01-11T09:28:45-05:00"
        }
    ],
    "field_registration_link": [
        {
            "uri": "http:\/\/www.jinochamospukic.biz",
            "title": "",
            "options": []
        }
    ]
}