{
    "_links": {
        "self": {
            "href": "http:\/\/botdemo.test\/resources\/commoveo-uxor-vel?_format=hal_json"
        },
        "type": {
            "href": "http:\/\/botdemo.test\/rest\/type\/node\/resource"
        },
        "http:\/\/botdemo.test\/rest\/relation\/node\/resource\/revision_uid": [
            {
                "href": "http:\/\/botdemo.test\/user\/1?_format=hal_json"
            }
        ],
        "http:\/\/botdemo.test\/rest\/relation\/node\/resource\/uid": [
            {
                "href": "http:\/\/botdemo.test\/user\/1?_format=hal_json",
                "lang": "en"
            }
        ],
        "http:\/\/botdemo.test\/rest\/relation\/node\/resource\/field_paragraphs": [
            {
                "href": "",
                "lang": "en"
            },
            {
                "href": "",
                "lang": "en"
            },
            {
                "href": "",
                "lang": "en"
            }
        ],
        "http:\/\/botdemo.test\/rest\/relation\/node\/resource\/field_photo": [
            {
                "href": "http:\/\/botdemo.test\/media\/8\/edit?_format=hal_json",
                "lang": "en"
            }
        ],
        "http:\/\/botdemo.test\/rest\/relation\/node\/resource\/field_resource_downloads": [
            {
                "href": "http:\/\/botdemo.test\/sites\/default\/files\/2020-08\/uVcBusSjIM.txt"
            }
        ],
        "http:\/\/botdemo.test\/rest\/relation\/node\/resource\/field_resource_type": [
            null
        ]
    },
    "uuid": [
        {
            "value": "152320ca-9d3c-4b90-b239-9e8cc4fbb2bc"
        }
    ],
    "langcode": [
        {
            "value": "en",
            "lang": "en"
        }
    ],
    "type": [
        {
            "target_id": "resource"
        }
    ],
    "revision_timestamp": [
        {
            "value": "2020-08-12T14:58:43+00:00",
            "format": "Y-m-d\\TH:i:sP"
        }
    ],
    "_embedded": {
        "http:\/\/botdemo.test\/rest\/relation\/node\/resource\/revision_uid": [
            {
                "_links": {
                    "self": {
                        "href": "http:\/\/botdemo.test\/user\/1?_format=hal_json"
                    },
                    "type": {
                        "href": "http:\/\/botdemo.test\/rest\/type\/user\/user"
                    }
                },
                "uuid": [
                    {
                        "value": "acdfcba1-884c-4b96-8000-232f9d10fe74"
                    }
                ]
            }
        ],
        "http:\/\/botdemo.test\/rest\/relation\/node\/resource\/uid": [
            {
                "_links": {
                    "self": {
                        "href": "http:\/\/botdemo.test\/user\/1?_format=hal_json"
                    },
                    "type": {
                        "href": "http:\/\/botdemo.test\/rest\/type\/user\/user"
                    }
                },
                "uuid": [
                    {
                        "value": "acdfcba1-884c-4b96-8000-232f9d10fe74"
                    }
                ],
                "lang": "en"
            }
        ],
        "http:\/\/botdemo.test\/rest\/relation\/node\/resource\/field_paragraphs": [
            {
                "_links": {
                    "self": {
                        "href": ""
                    },
                    "type": {
                        "href": "http:\/\/botdemo.test\/rest\/type\/paragraph\/image_grid"
                    }
                },
                "uuid": [
                    {
                        "value": "464be043-493c-4ceb-b4f5-3fc82b38174a"
                    }
                ],
                "lang": "en",
                "target_revision_id": "679"
            },
            {
                "_links": {
                    "self": {
                        "href": ""
                    },
                    "type": {
                        "href": "http:\/\/botdemo.test\/rest\/type\/paragraph\/text"
                    }
                },
                "uuid": [
                    {
                        "value": "b2880664-f30c-423a-a737-00211d31f334"
                    }
                ],
                "lang": "en",
                "target_revision_id": "680"
            },
            {
                "_links": {
                    "self": {
                        "href": ""
                    },
                    "type": {
                        "href": "http:\/\/botdemo.test\/rest\/type\/paragraph\/slideshow"
                    }
                },
                "uuid": [
                    {
                        "value": "6ef8b636-600f-4514-b06d-063224fa35a4"
                    }
                ],
                "lang": "en",
                "target_revision_id": "683"
            }
        ],
        "http:\/\/botdemo.test\/rest\/relation\/node\/resource\/field_photo": [
            {
                "_links": {
                    "self": {
                        "href": "http:\/\/botdemo.test\/media\/8\/edit?_format=hal_json"
                    },
                    "type": {
                        "href": "http:\/\/botdemo.test\/rest\/type\/media\/image"
                    }
                },
                "uuid": [
                    {
                        "value": "0e5b6d9a-67c9-4f0b-9f59-6d0d9c1be057"
                    }
                ],
                "lang": "en"
            }
        ],
        "http:\/\/botdemo.test\/rest\/relation\/node\/resource\/field_resource_downloads": [
            {
                "_links": {
                    "self": {
                        "href": "http:\/\/botdemo.test\/sites\/default\/files\/2020-08\/uVcBusSjIM.txt"
                    },
                    "type": {
                        "href": "http:\/\/botdemo.test\/rest\/type\/file\/file"
                    }
                },
                "uuid": [
                    {
                        "value": "b1835d97-e7b9-438e-a49a-c65c6fe22307"
                    }
                ]
            }
        ],
        "http:\/\/botdemo.test\/rest\/relation\/node\/resource\/field_resource_type": [
            null
        ]
    },
    "status": [
        {
            "value": true,
            "lang": "en"
        }
    ],
    "title": [
        {
            "value": "Commoveo Uxor Vel",
            "lang": "en"
        }
    ],
    "created": [
        {
            "value": "2020-08-10T14:42:00+00:00",
            "lang": "en",
            "format": "Y-m-d\\TH:i:sP"
        }
    ],
    "changed": [
        {
            "value": "2020-08-12T14:58:43+00:00",
            "lang": "en",
            "format": "Y-m-d\\TH:i:sP"
        }
    ],
    "promote": [
        {
            "value": false,
            "lang": "en"
        }
    ],
    "sticky": [
        {
            "value": false,
            "lang": "en"
        }
    ],
    "default_langcode": [
        {
            "value": true,
            "lang": "en"
        }
    ],
    "revision_translation_affected": [
        {
            "value": true,
            "lang": "en"
        }
    ],
    "metatag": [
        {
            "value": {
                "title": "Commoveo Uxor Vel | BackOffice Theme",
                "canonical_url": "http:\/\/botdemo.test\/resources\/commoveo-uxor-vel",
                "description": "Enim exputo hos pagus suscipere. Camur ibidem ludus nutus. Brevitas eros incassum luctus minim modo probo refoveo. Abdo abluo blandit cui haero huic iriure laoreet quadrum wisi. Adipiscing duis elit facilisis huic inhibeo pala probo vindico. Ea facilisis huic nibh persto secundum. Abico ea lobortis pertineo ratis.\nCausa esse luptatum mos natu nibh quibus tincidunt uxor. Letalis pertineo vindico. Cogo cui huic lucidus ludus tego utinam. Camur hos lenis nobis paulatim refoveo suscipere uxor virtus. Augue esse pecus pertineo quia. Acsi caecus consectetuer genitus incassum iriure metuo typicus vel. Comis ille nisl obruo patria tincidunt. Abdo conventio elit eu euismod saepius tation volutpat ymo zelus. Dolor illum interdico iustum mauris odio olim os saepius zelus.\nAptent huic iriure iustum nunc obruo pecus secundum usitas vulpes. Abigo elit iusto letalis wisi. Cogo diam letalis neque refoveo similis vero. Conventio exerci in luptatum pagus quadrum si singularis utinam verto. Abico ad caecus cogo enim lucidus secundum torqueo vicis.\nAptent conventio distineo eligo gemino hos iusto paulatim praesent ratis. Abigo capto commoveo damnum gilvus ille iusto macto molior persto. Causa haero magna quidne te. Conventio eligo enim immitto ulciscor. Damnum minim neo paratus plaga tincidunt. At euismod pagus. Causa facilisis ideo nunc velit.\nAmet gravis nimis nisl oppeto scisco utinam vindico. Exputo macto mauris roto sit te tego. Amet dolore fere lucidus mauris pecus premo quibus singularis tego.\nEt quae ratis te utrum. Aptent brevitas defui huic in lucidus ludus persto tincidunt turpis. Adipiscing autem ex iaceo validus venio. Abbas commodo te. Abluo exerci laoreet lobortis minim mos roto. Commoveo immitto magna pertineo. Autem cui damnum fere huic macto melior tego utrum. Ad eu gilvus inhibeo metuo rusticus te vindico virtus.\nAbico dignissim ea similis suscipere. Brevitas capto jugis occuro os quibus tamen ulciscor. Consequat esse exerci huic laoreet metuo proprius roto tamen verto.\nAbico conventio gemino letalis. Diam erat natu quadrum tation utinam. Abico dignissim probo sit vindico. Antehabeo brevitas defui eu exputo facilisis melior nunc pneum vindico. Amet capto comis decet macto meus neque torqueo ulciscor usitas.\nAd caecus camur dignissim esse nobis olim pneum premo sagaciter. Plaga praesent sed. Autem duis nutus pertineo secundum typicus validus vindico. Abbas ea fere iriure suscipere tego. Cui et nunc obruo. Ad adipiscing esse loquor natu odio. Aptent diam eros gravis illum nibh nobis praesent uxor ymo. Defui laoreet turpis ulciscor. Aliquam esca ille verto. Caecus jus laoreet. Camur dolore feugiat hendrerit hos mauris quidne.\nAccumsan oppeto sino valetudo. Facilisis iusto qui refero vel vereor vindico. Commoveo damnum elit exerci lenis minim obruo oppeto quidne valetudo. Adipiscing antehabeo hendrerit hos immitto nostrud pneum ut. Brevitas dolus enim in pertineo plaga quadrum verto. Lenis luptatum praesent.\nAbdo adipiscing defui huic laoreet pertineo populus premo tincidunt volutpat. Ibidem ludus pagus plaga praesent uxor. Bene commodo defui eligo magna nimis nisl praesent ratis wisi. Camur magna nutus proprius singularis sino sit utrum. Cui dolore eligo quae usitas voco.\nFacilisis patria torqueo. Ad aliquam bene dignissim eu jus populus praemitto sit tum. Consectetuer diam neque tego. Commoveo dolus magna oppeto si torqueo ymo. Diam roto saepius tation venio. Adipiscing capto cogo genitus olim pneum ullamcorper valetudo. Camur esca valde virtus."
            }
        }
    ],
    "path": [
        {
            "alias": "\/resources\/commoveo-uxor-vel",
            "pid": 438,
            "langcode": "en",
            "lang": "en"
        }
    ],
    "body": [
        {
            "value": "Enim exputo hos pagus suscipere. Camur ibidem ludus nutus. Brevitas eros incassum luctus minim modo probo refoveo. Abdo abluo blandit cui haero huic iriure laoreet quadrum wisi. Adipiscing duis elit facilisis huic inhibeo pala probo vindico. Ea facilisis huic nibh persto secundum. Abico ea lobortis pertineo ratis.\n\nCausa esse luptatum mos natu nibh quibus tincidunt uxor. Letalis pertineo vindico. Cogo cui huic lucidus ludus tego utinam. Camur hos lenis nobis paulatim refoveo suscipere uxor virtus. Augue esse pecus pertineo quia. Acsi caecus consectetuer genitus incassum iriure metuo typicus vel. Comis ille nisl obruo patria tincidunt. Abdo conventio elit eu euismod saepius tation volutpat ymo zelus. Dolor illum interdico iustum mauris odio olim os saepius zelus.\n\nAptent huic iriure iustum nunc obruo pecus secundum usitas vulpes. Abigo elit iusto letalis wisi. Cogo diam letalis neque refoveo similis vero. Conventio exerci in luptatum pagus quadrum si singularis utinam verto. Abico ad caecus cogo enim lucidus secundum torqueo vicis.\n\nAptent conventio distineo eligo gemino hos iusto paulatim praesent ratis. Abigo capto commoveo damnum gilvus ille iusto macto molior persto. Causa haero magna quidne te. Conventio eligo enim immitto ulciscor. Damnum minim neo paratus plaga tincidunt. At euismod pagus. Causa facilisis ideo nunc velit.\n\nAmet gravis nimis nisl oppeto scisco utinam vindico. Exputo macto mauris roto sit te tego. Amet dolore fere lucidus mauris pecus premo quibus singularis tego.\n\nEt quae ratis te utrum. Aptent brevitas defui huic in lucidus ludus persto tincidunt turpis. Adipiscing autem ex iaceo validus venio. Abbas commodo te. Abluo exerci laoreet lobortis minim mos roto. Commoveo immitto magna pertineo. Autem cui damnum fere huic macto melior tego utrum. Ad eu gilvus inhibeo metuo rusticus te vindico virtus.\n\nAbico dignissim ea similis suscipere. Brevitas capto jugis occuro os quibus tamen ulciscor. Consequat esse exerci huic laoreet metuo proprius roto tamen verto.\n\nAbico conventio gemino letalis. Diam erat natu quadrum tation utinam. Abico dignissim probo sit vindico. Antehabeo brevitas defui eu exputo facilisis melior nunc pneum vindico. Amet capto comis decet macto meus neque torqueo ulciscor usitas.\n\nAd caecus camur dignissim esse nobis olim pneum premo sagaciter. Plaga praesent sed. Autem duis nutus pertineo secundum typicus validus vindico. Abbas ea fere iriure suscipere tego. Cui et nunc obruo. Ad adipiscing esse loquor natu odio. Aptent diam eros gravis illum nibh nobis praesent uxor ymo. Defui laoreet turpis ulciscor. Aliquam esca ille verto. Caecus jus laoreet. Camur dolore feugiat hendrerit hos mauris quidne.\n\nAccumsan oppeto sino valetudo. Facilisis iusto qui refero vel vereor vindico. Commoveo damnum elit exerci lenis minim obruo oppeto quidne valetudo. Adipiscing antehabeo hendrerit hos immitto nostrud pneum ut. Brevitas dolus enim in pertineo plaga quadrum verto. Lenis luptatum praesent.\n\nAbdo adipiscing defui huic laoreet pertineo populus premo tincidunt volutpat. Ibidem ludus pagus plaga praesent uxor. Bene commodo defui eligo magna nimis nisl praesent ratis wisi. Camur magna nutus proprius singularis sino sit utrum. Cui dolore eligo quae usitas voco.\n\nFacilisis patria torqueo. Ad aliquam bene dignissim eu jus populus praemitto sit tum. Consectetuer diam neque tego. Commoveo dolus magna oppeto si torqueo ymo. Diam roto saepius tation venio. Adipiscing capto cogo genitus olim pneum ullamcorper valetudo. Camur esca valde virtus.\n\n",
            "format": "plain_text",
            "processed": "<p>Enim exputo hos pagus suscipere. Camur ibidem ludus nutus. Brevitas eros incassum luctus minim modo probo refoveo. Abdo abluo blandit cui haero huic iriure laoreet quadrum wisi. Adipiscing duis elit facilisis huic inhibeo pala probo vindico. Ea facilisis huic nibh persto secundum. Abico ea lobortis pertineo ratis.<\/p>\n<p>Causa esse luptatum mos natu nibh quibus tincidunt uxor. Letalis pertineo vindico. Cogo cui huic lucidus ludus tego utinam. Camur hos lenis nobis paulatim refoveo suscipere uxor virtus. Augue esse pecus pertineo quia. Acsi caecus consectetuer genitus incassum iriure metuo typicus vel. Comis ille nisl obruo patria tincidunt. Abdo conventio elit eu euismod saepius tation volutpat ymo zelus. Dolor illum interdico iustum mauris odio olim os saepius zelus.<\/p>\n<p>Aptent huic iriure iustum nunc obruo pecus secundum usitas vulpes. Abigo elit iusto letalis wisi. Cogo diam letalis neque refoveo similis vero. Conventio exerci in luptatum pagus quadrum si singularis utinam verto. Abico ad caecus cogo enim lucidus secundum torqueo vicis.<\/p>\n<p>Aptent conventio distineo eligo gemino hos iusto paulatim praesent ratis. Abigo capto commoveo damnum gilvus ille iusto macto molior persto. Causa haero magna quidne te. Conventio eligo enim immitto ulciscor. Damnum minim neo paratus plaga tincidunt. At euismod pagus. Causa facilisis ideo nunc velit.<\/p>\n<p>Amet gravis nimis nisl oppeto scisco utinam vindico. Exputo macto mauris roto sit te tego. Amet dolore fere lucidus mauris pecus premo quibus singularis tego.<\/p>\n<p>Et quae ratis te utrum. Aptent brevitas defui huic in lucidus ludus persto tincidunt turpis. Adipiscing autem ex iaceo validus venio. Abbas commodo te. Abluo exerci laoreet lobortis minim mos roto. Commoveo immitto magna pertineo. Autem cui damnum fere huic macto melior tego utrum. Ad eu gilvus inhibeo metuo rusticus te vindico virtus.<\/p>\n<p>Abico dignissim ea similis suscipere. Brevitas capto jugis occuro os quibus tamen ulciscor. Consequat esse exerci huic laoreet metuo proprius roto tamen verto.<\/p>\n<p>Abico conventio gemino letalis. Diam erat natu quadrum tation utinam. Abico dignissim probo sit vindico. Antehabeo brevitas defui eu exputo facilisis melior nunc pneum vindico. Amet capto comis decet macto meus neque torqueo ulciscor usitas.<\/p>\n<p>Ad caecus camur dignissim esse nobis olim pneum premo sagaciter. Plaga praesent sed. Autem duis nutus pertineo secundum typicus validus vindico. Abbas ea fere iriure suscipere tego. Cui et nunc obruo. Ad adipiscing esse loquor natu odio. Aptent diam eros gravis illum nibh nobis praesent uxor ymo. Defui laoreet turpis ulciscor. Aliquam esca ille verto. Caecus jus laoreet. Camur dolore feugiat hendrerit hos mauris quidne.<\/p>\n<p>Accumsan oppeto sino valetudo. Facilisis iusto qui refero vel vereor vindico. Commoveo damnum elit exerci lenis minim obruo oppeto quidne valetudo. Adipiscing antehabeo hendrerit hos immitto nostrud pneum ut. Brevitas dolus enim in pertineo plaga quadrum verto. Lenis luptatum praesent.<\/p>\n<p>Abdo adipiscing defui huic laoreet pertineo populus premo tincidunt volutpat. Ibidem ludus pagus plaga praesent uxor. Bene commodo defui eligo magna nimis nisl praesent ratis wisi. Camur magna nutus proprius singularis sino sit utrum. Cui dolore eligo quae usitas voco.<\/p>\n<p>Facilisis patria torqueo. Ad aliquam bene dignissim eu jus populus praemitto sit tum. Consectetuer diam neque tego. Commoveo dolus magna oppeto si torqueo ymo. Diam roto saepius tation venio. Adipiscing capto cogo genitus olim pneum ullamcorper valetudo. Camur esca valde virtus.<\/p>\n",
            "summary": "Enim exputo hos pagus suscipere. Camur ibidem ludus nutus. Brevitas eros incassum luctus minim modo probo refoveo. Abdo abluo blandit cui haero huic iriure laoreet quadrum wisi. Adipiscing duis elit facilisis huic inhibeo pala probo vindico. Ea facilisis huic nibh persto secundum. Abico ea lobortis pertineo ratis.\n\nCausa esse luptatum mos natu nibh quibus tincidunt uxor. Letalis pertineo vindico. Cogo cui huic lucidus ludus tego utinam. Camur hos lenis nobis paulatim refoveo suscipere uxor virtus. Augue esse pecus pertineo quia. Acsi caecus consectetuer genitus incassum iriure metuo typicus vel. Comis ille nisl obruo patria tincidunt. Abdo conventio elit eu euismod saepius tation volutpat ymo zelus. Dolor illum interdico iustum mauris odio olim os saepius zelus.\n\nAptent huic iriure iustum nunc obruo pecus secundum usitas vulpes. Abigo elit iusto letalis wisi. Cogo diam letalis neque refoveo similis vero. Conventio exerci in luptatum pagus quadrum si singularis utinam verto. Abico ad caecus cogo enim lucidus secundum torqueo vicis.\n\nAptent conventio distineo eligo gemino hos iusto paulatim praesent ratis. Abigo capto commoveo damnum gilvus ille iusto macto molior persto. Causa haero magna quidne te. Conventio eligo enim immitto ulciscor. Damnum minim neo paratus plaga tincidunt. At euismod pagus. Causa facilisis ideo nunc velit.\n\nAmet gravis nimis nisl oppeto scisco utinam vindico. Exputo macto mauris roto sit te tego. Amet dolore fere lucidus mauris pecus premo quibus singularis tego.\n\nEt quae ratis te utrum. Aptent brevitas defui huic in lucidus ludus persto tincidunt turpis. Adipiscing autem ex iaceo validus venio. Abbas commodo te. Abluo exerci laoreet lobortis minim mos roto. Commoveo immitto magna pertineo. Autem cui damnum fere huic macto melior tego utrum. Ad eu gilvus inhibeo metuo rusticus te vindico virtus.\n\nAbico dignissim ea similis suscipere. Brevitas capto jugis occuro os quibus tamen ulciscor. Consequat esse exerci huic laoreet metuo proprius roto tamen verto.\n\nAbico conventio gemino letalis. Diam erat natu quadrum tation utinam. Abico dignissim probo sit vindico. Antehabeo brevitas defui eu exputo facilisis melior nunc pneum vindico. Amet capto comis decet macto meus neque torqueo ulciscor usitas.\n\nAd caecus camur dignissim esse nobis olim pneum premo sagaciter. Plaga praesent sed. Autem duis nutus pertineo secundum typicus validus vindico. Abbas ea fere iriure suscipere tego. Cui et nunc obruo. Ad adipiscing esse loquor natu odio. Aptent diam eros gravis illum nibh nobis praesent uxor ymo. Defui laoreet turpis ulciscor. Aliquam esca ille verto. Caecus jus laoreet. Camur dolore feugiat hendrerit hos mauris quidne.\n\nAccumsan oppeto sino valetudo. Facilisis iusto qui refero vel vereor vindico. Commoveo damnum elit exerci lenis minim obruo oppeto quidne valetudo. Adipiscing antehabeo hendrerit hos immitto nostrud pneum ut. Brevitas dolus enim in pertineo plaga quadrum verto. Lenis luptatum praesent.\n\nAbdo adipiscing defui huic laoreet pertineo populus premo tincidunt volutpat. Ibidem ludus pagus plaga praesent uxor. Bene commodo defui eligo magna nimis nisl praesent ratis wisi. Camur magna nutus proprius singularis sino sit utrum. Cui dolore eligo quae usitas voco.\n\nFacilisis patria torqueo. Ad aliquam bene dignissim eu jus populus praemitto sit tum. Consectetuer diam neque tego. Commoveo dolus magna oppeto si torqueo ymo. Diam roto saepius tation venio. Adipiscing capto cogo genitus olim pneum ullamcorper valetudo. Camur esca valde virtus.\n\n",
            "lang": "en"
        }
    ],
    "field_resource_links": [
        {
            "uri": "http:\/\/www.frakukacruv.net",
            "title": "Dolor elit mauris molior.",
            "options": []
        }
    ]
}