{
    "_links": {
        "self": {
            "href": "http:\/\/botdemo.test\/sites\/default\/files\/2020-08\/generateImage_TzVdPl.jpeg"
        },
        "type": {
            "href": "http:\/\/botdemo.test\/rest\/type\/file\/file"
        },
        "http:\/\/botdemo.test\/rest\/relation\/file\/file\/uid": [
            {
                "href": "http:\/\/botdemo.test\/user\/1?_format=hal_json"
            }
        ]
    },
    "uuid": [
        {
            "value": "fe8883e9-43c3-45c2-8a73-e06a238d9261"
        }
    ],
    "langcode": [
        {
            "value": "en"
        }
    ],
    "_embedded": {
        "http:\/\/botdemo.test\/rest\/relation\/file\/file\/uid": [
            {
                "_links": {
                    "self": {
                        "href": "http:\/\/botdemo.test\/user\/1?_format=hal_json"
                    },
                    "type": {
                        "href": "http:\/\/botdemo.test\/rest\/type\/user\/user"
                    }
                },
                "uuid": [
                    {
                        "value": "acdfcba1-884c-4b96-8000-232f9d10fe74"
                    }
                ]
            }
        ]
    },
    "filename": [
        {
            "value": "generateImage_TzVdPl.jpeg"
        }
    ],
    "uri": [
        {
            "value": "public:\/\/2020-08\/generateImage_TzVdPl.jpeg",
            "url": "\/sites\/default\/files\/2020-08\/generateImage_TzVdPl.jpeg"
        }
    ],
    "filemime": [
        {
            "value": "image\/jpeg"
        }
    ],
    "filesize": [
        {
            "value": 9518
        }
    ],
    "status": [
        {
            "value": true
        }
    ],
    "created": [
        {
            "value": "2020-08-11T15:35:37+00:00",
            "format": "Y-m-d\\TH:i:sP"
        }
    ],
    "changed": [
        {
            "value": "2020-08-11T15:35:37+00:00",
            "format": "Y-m-d\\TH:i:sP"
        }
    ]
}